Metadata-Version: 2.1
Name: gb-test-dis
Version: 0.1
Summary: Gaussian distributions
Home-page: UNKNOWN
License: UNKNOWN
Platform: UNKNOWN
